generate_env_sample/__init__.py
generate_env_sample/main.py
generate_env_sample-0.1.1.dist-info/WHEEL
generate_env_sample-0.1.1.dist-info/entry_points.txt
generate_env_sample-0.1.1.dist-info/METADATA
generate_env_sample-0.1.1.dist-info/RECORD
