Metadata-Version: 2.3
Name: generate-env-sample
Version: 0.1.1
Summary: A simple CLI tool to generate .env.sample files from existing .env files, preserving comments and empty lines.
Keywords: cli,env,sample,python,typer,environment-variables
Author: Heshinth P
Author-email: heshinth@gmail.com
Classifier: Intended Audience :: Developers
Classifier: License :: OSI Approved :: MIT License
Classifier: Programming Language :: Python :: 3.11
Requires-Dist: typer-slim>=0.17.4
Requires-Python: >=3.11
Project-URL: Issues, https://github.com/heshinth/generate-env-sample/issues
Project-URL: Repository, https://github.com/heshinth/generate-env-sample.git
